MANIFEST.in
README.md
requirements.txt
setup.py
sshrun.py
sshrun.egg-info/PKG-INFO
sshrun.egg-info/SOURCES.txt
sshrun.egg-info/dependency_links.txt
sshrun.egg-info/entry_points.txt
sshrun.egg-info/requires.txt
sshrun.egg-info/top_level.txt