Metadata-Version: 2.1
Name: sshrun
Version: 0.1.0
Summary: Run command on remote server via ssh channel.
Home-page: UNKNOWN
Author: zencore-cn
Author-email: info@zencore.cn
License: MIT
Keywords: sshrun
Platform: UNKNOWN
Classifier: Development Status :: 5 - Production/Stable
Classifier: Intended Audience :: Developers
Classifier: Topic :: Software Development :: Libraries :: Python Modules
Classifier: License :: OSI Approved :: MIT License
Classifier: Programming Language :: Python :: 3
Classifier: Programming Language :: Python :: 3 :: Only
Requires: click
Requires: paramiko
